cosmic_toolkit/__init__.py
cosmic_toolkit/message_bus.py
cosmic_toolkit/models.py
cosmic_toolkit/repository.py
cosmic_toolkit/types.py
cosmic_toolkit/unit_of_work.py
test/__init__.py
test/conftest.py
test/test_message_bus.py
test/test_models.py
test/test_repository.py
test/test_unit_of_work.py
cosmic_toolkit-0.6.1.dist-info/LICENSE
cosmic_toolkit-0.6.1.dist-info/METADATA
cosmic_toolkit-0.6.1.dist-info/WHEEL
cosmic_toolkit-0.6.1.dist-info/top_level.txt
cosmic_toolkit-0.6.1.dist-info/RECORD
