Metadata-Version: 2.1
Name: cosmic-toolkit
Version: 0.6.1
Summary: Domain-Driven Design (DDD) toolkit to quickly develop complex apps
Home-page: https://github.com/fsgsmartbuildings/cosmic-toolkit
License: UNKNOWN
Keywords: cosmic,messagebus,domain driven design,clean architecture
Platform: UNKNOWN
Classifier: Development Status :: 3 - Alpha
Classifier: Intended Audience :: Developers
Classifier: License :: OSI Approved :: MIT License
Classifier: Programming Language :: Python :: 3.7
Classifier: Programming Language :: Python :: 3.8
Classifier: Programming Language :: Python :: 3.9
Requires-Python: >=3.7
License-File: LICENSE
Requires-Dist: pydantic (>=1.8.2)
